Metadata-Version: 2.1
Name: ebay-product-scraper
Version: 1.0.1
Summary: A python library to scrape product data on ebay automatically.
Home-page: https://datakund.com
Author: DataKund
Author-email: datakund@gmail.com
License: Apache License 2.0
Keywords: ebay python bot_studio scraper data product info web-scraping
Platform: UNKNOWN
